protobuf_to_pydantic/__init__.py
protobuf_to_pydantic/__main__.py
protobuf_to_pydantic/__version__.py
protobuf_to_pydantic/_pydantic_adapter.py
protobuf_to_pydantic/cli.py
protobuf_to_pydantic/constant.py
protobuf_to_pydantic/contrib/__init__.py
protobuf_to_pydantic/contrib/proto_parser.py
protobuf_to_pydantic/customer_con_type/__init__.py
protobuf_to_pydantic/customer_con_type/v1.py
protobuf_to_pydantic/customer_con_type/v2.py
protobuf_to_pydantic/customer_validator/__init__.py
protobuf_to_pydantic/customer_validator/rule.py
protobuf_to_pydantic/customer_validator/v1.py
protobuf_to_pydantic/customer_validator/v2.py
protobuf_to_pydantic/exceptions.py
protobuf_to_pydantic/field_info_rule/__init__.py
protobuf_to_pydantic/field_info_rule/field_info_param.py
protobuf_to_pydantic/field_info_rule/protobuf_option_to_field_info/__init__.py
protobuf_to_pydantic/field_info_rule/protobuf_option_to_field_info/base.py
protobuf_to_pydantic/field_info_rule/protobuf_option_to_field_info/comment.py
protobuf_to_pydantic/field_info_rule/protobuf_option_to_field_info/desc.py
protobuf_to_pydantic/field_info_rule/protobuf_option_to_field_info/types.py
protobuf_to_pydantic/field_info_rule/types.py
protobuf_to_pydantic/gen_code.py
protobuf_to_pydantic/gen_model.py
protobuf_to_pydantic/get_message_option/__init__.py
protobuf_to_pydantic/get_message_option/from_message_option/__init__.py
protobuf_to_pydantic/get_message_option/from_message_option/base.py
protobuf_to_pydantic/get_message_option/from_message_option/from_p2p.py
protobuf_to_pydantic/get_message_option/from_message_option/from_pgv.py
protobuf_to_pydantic/get_message_option/from_proto_file.py
protobuf_to_pydantic/get_message_option/from_pyi_file.py
protobuf_to_pydantic/get_message_option/utils.py
protobuf_to_pydantic/grpc_types.py
protobuf_to_pydantic/plugin/__init__.py
protobuf_to_pydantic/plugin/__main__.py
protobuf_to_pydantic/plugin/code_gen.py
protobuf_to_pydantic/plugin/config.py
protobuf_to_pydantic-0.3.3.1.dist-info/LICENSE
protobuf_to_pydantic-0.3.3.1.dist-info/METADATA
protobuf_to_pydantic-0.3.3.1.dist-info/WHEEL
protobuf_to_pydantic-0.3.3.1.dist-info/entry_points.txt
protobuf_to_pydantic-0.3.3.1.dist-info/RECORD
