Metadata-Version: 2.1
Name: protobuf_to_pydantic
Version: 0.3.3.1
Summary: Generate the `pydantic.BaseModel` class (and the corresponding source code) with parameter verification function through the Protobuf file
Home-page: https://github.com/so1n/protobuf_to_pydantic
License: Apache Software License
Author: So1n
Author-email: so1n897046026@gmail.com
Requires-Python: >=3.7,<4.0
Classifier: License :: Other/Proprietary License
Classifier: Programming Language :: Python :: 3
Classifier: Programming Language :: Python :: 3.7
Classifier: Programming Language :: Python :: 3.8
Classifier: Programming Language :: Python :: 3.9
Classifier: Programming Language :: Python :: 3.10
Classifier: Programming Language :: Python :: 3.11
Classifier: Programming Language :: Python :: 3.12
Provides-Extra: all
Provides-Extra: lark
Provides-Extra: mypy-protobuf
Provides-Extra: toml
Requires-Dist: lark (>=1.1.2,<2.0.0) ; extra == "lark" or extra == "all"
Requires-Dist: mypy-protobuf (>=3.2.0,<4.0.0) ; extra == "mypy-protobuf" or extra == "all"
Requires-Dist: protobuf (>=3.20.3)
Requires-Dist: pydantic (>=1.9.2,<3.0.0,!=2.5.0,!=2.9.0)
Requires-Dist: toml (>=0.10.2,<0.11.0) ; extra == "toml" or extra == "all"
Project-URL: Repository, https://github.com/so1n/protobuf_to_pydantic
